pydevtool/__init__.py
pydevtool/cli.py
pydevtool/lint_flake8.py
pydevtool/lint_pycodestyle.py
pydevtool/lint_pyflakes.py
pydevtool/path.py
pydevtool/reporter.py
pydevtool-0.3.0.dist-info/AUTHORS
pydevtool-0.3.0.dist-info/LICENSE
pydevtool-0.3.0.dist-info/METADATA
pydevtool-0.3.0.dist-info/WHEEL
pydevtool-0.3.0.dist-info/top_level.txt
pydevtool-0.3.0.dist-info/RECORD
